pylsp_refactor/__init__.py
pylsp_refactor/actions/__init__.py
pylsp_refactor/actions/base.py
pylsp_refactor/actions/introduce_variable_under_cursor.py
pylsp_refactor/plugin.py
pylsp_refactor/regexes.py
pylsp_refactor/utils.py
pylsp_refactor-0.1.0.dist-info/AUTHORS.md
pylsp_refactor-0.1.0.dist-info/LICENSE
pylsp_refactor-0.1.0.dist-info/METADATA
pylsp_refactor-0.1.0.dist-info/WHEEL
pylsp_refactor-0.1.0.dist-info/entry_points.txt
pylsp_refactor-0.1.0.dist-info/RECORD
