Metadata-Version: 2.1
Name: pylsp-refactor
Version: 0.1.0
Summary: Refactoring tools for python-lsp-server
Home-page: https://github.com/venomlab/pylsp-refactor
License: MIT
Author: Dmytro Selishchev
Author-email: zibertscrem@gmail.com
Requires-Python: >=3.10,<4.0
Classifier: License :: OSI Approved :: MIT License
Classifier: Programming Language :: Python :: 3
Classifier: Programming Language :: Python :: 3.10
Classifier: Programming Language :: Python :: 3.11
Classifier: Programming Language :: Python :: 3.12
Requires-Dist: jedi
Requires-Dist: python-lsp-server
Project-URL: Repository, https://github.com/venomlab/pylsp-refactor
